streamlit_drawable_canvas/__init__.py
streamlit_drawable_canvas/frontend/build/asset-manifest.json
streamlit_drawable_canvas/frontend/build/index.html
streamlit_drawable_canvas/frontend/build/static/css/main.8802268d.chunk.css
streamlit_drawable_canvas/frontend/build/static/css/main.8802268d.chunk.css.map
streamlit_drawable_canvas/frontend/build/static/js/2.3a63bcf0.chunk.js
streamlit_drawable_canvas/frontend/build/static/js/2.3a63bcf0.chunk.js.LICENSE.txt
streamlit_drawable_canvas/frontend/build/static/js/2.3a63bcf0.chunk.js.map
streamlit_drawable_canvas/frontend/build/static/js/main.80185090.chunk.js
streamlit_drawable_canvas/frontend/build/static/js/main.80185090.chunk.js.map
streamlit_drawable_canvas/frontend/build/static/js/runtime-main.3def19be.js
streamlit_drawable_canvas/frontend/build/static/js/runtime-main.3def19be.js.map
streamlit_drawable_canvas-0.9.3.dist-info/LICENSE
streamlit_drawable_canvas-0.9.3.dist-info/METADATA
streamlit_drawable_canvas-0.9.3.dist-info/WHEEL
streamlit_drawable_canvas-0.9.3.dist-info/top_level.txt
streamlit_drawable_canvas-0.9.3.dist-info/RECORD
