Metadata-Version: 2.1
Name: streamlit-drawable-canvas
Version: 0.9.3
Summary: A Streamlit custom component for a free drawing canvas using Fabric.js.
Home-page: https://github.com/andfanilo/streamlit-drawable-canvas
Author: Fanilo ANDRIANASOLO
Author-email: contact@andfanilo.com
License: UNKNOWN
Platform: UNKNOWN
Requires-Python: >=3.6
